monotonic_attention/__init__.py
monotonic_attention/py.typed
monotonic_attention/requirements.txt
monotonic_attention/utils.py
monotonic_attention/many_to_many/__init__.py
monotonic_attention/many_to_many/cpu_log.py
monotonic_attention/many_to_many/cpu_log_faster.py
monotonic_attention/many_to_many/cpu_simple.py
monotonic_attention/many_to_many/cpu_simple_faster.py
monotonic_attention/one_to_many/__init__.py
monotonic_attention/one_to_many/cpu_log.py
monotonic_attention/one_to_many/triton/__init__.py
monotonic_attention/one_to_many/triton/gpu_log.py
monotonic_attention-0.0.4.dist-info/LICENSE
monotonic_attention-0.0.4.dist-info/METADATA
monotonic_attention-0.0.4.dist-info/WHEEL
monotonic_attention-0.0.4.dist-info/top_level.txt
monotonic_attention-0.0.4.dist-info/RECORD
