Metadata-Version: 2.1
Name: monotonic-attention
Version: 0.0.4
Summary: Monotonic attention implementation
Home-page: https://github.com/codekansas/monotonic-attention
Author: Benjamin Bolte
Classifier: Development Status :: 4 - Beta
Classifier: Intended Audience :: Developers
Classifier: Topic :: Scientific/Engineering :: Artificial Intelligence
Classifier: License :: OSI Approved :: MIT License
Classifier: Programming Language :: Python :: 3
Requires-Python: >=3.10
License-File: LICENSE
Requires-Dist: numpy
Requires-Dist: torch
Provides-Extra: dev
Requires-Dist: black ; extra == 'dev'
Requires-Dist: darglint ; extra == 'dev'
Requires-Dist: mypy ; extra == 'dev'
Requires-Dist: pytest ; extra == 'dev'
Requires-Dist: pytest-timeout ; extra == 'dev'
Requires-Dist: ruff ; extra == 'dev'
